{
  "ComponentIndexes": {},
  "ControlUniqueGuids": {},
  "ControlUniqueIds": {
    "address_card": 487,
    "address_card_1": 383,
    "address_input": 489,
    "address_input_1": 385,
    "address_label": 488,
    "address_label_1": 384,
    "App": 1,
    "BILLABILITY_Column1_1": 272,
    "BILLABILITY_DataCard PRMp1_1": 44,
    "BILLABILITY_DataCardOCFP": 604,
    "BILLABILITY_LTMDataCard": 161,
    "BILLABILITY_LTMDataCard2": 422,
    "BILLABILITY_OTDataCard": 223,
    "BILLABILITY_OTDataCard1": 541,
    "BILLABILITY_PRMDataCard2_2": 320,
    "btnFirstPageNext": 339,
    "btnLTMultipleBack": 171,
    "btnLTMultipleBack_1": 439,
    "btnLTMultipleBack_2": 570,
    "btnLTMultipleBack_3": 495,
    "btnLTMultipleBack_4": 391,
    "btnLTMultipleReview": 172,
    "btnLTMultipleReview_1": 440,
    "btnLTMultipleReview_2": 571,
    "btnLTRemove": 432,
    "btnLTRemove_1": 390,
    "btnOCEPBack": 119,
    "btnOCEPUpdate": 120,
    "btnOCFPBack": 638,
    "btnOCFPReview": 639,
    "btnOCFPSave": 637,
    "btnOCSPBack": 281,
    "btnOCSPEdit": 258,
    "btnOCSPRemove": 259,
    "btnOCSPSubmit": 282,
    "btnOTBack": 252,
    "btnOTRemove": 569,
    "btnOTReview": 253,
    "btnOTSave": 251,
    "btnPRMultipleBackp1_1": 54,
    "btnPRMultipleBackp2_1": 331,
    "btnPRMultipleReviewp1_1": 55,
    "btnPRMultipleSubmitp2_1": 332,
    "btnPRRemovep2_3": 330,
    "BUSINESS UNIT_Column1_1": 266,
    "BUSINESS UNIT_DataCard PRMp1_1": 26,
    "BUSINESS UNIT_DataCardOCFP": 608,
    "BUSINESS UNIT_LTMDataCard": 143,
    "BUSINESS UNIT_LTMDataCard2": 404,
    "BUSINESS UNIT_OTDataCard": 193,
    "BUSINESS UNIT_OTDataCard1": 511,
    "BUSINESS UNIT_PRMDataCard_4": 302,
    "Button1": 636,
    "Button2": 494,
    "Button3": 170,
    "Button4": 53,
    "campaign_card": 472,
    "campaign_card_1": 368,
    "CAMPAIGN_Column1_1": 270,
    "campaign_label": 473,
    "campaign_label_1": 369,
    "campaign_value": 474,
    "campaign_value_1": 370,
    "cbLTMultipleBillability": 162,
    "cbLTMultipleBusUnit": 144,
    "cbLTMultipleClient": 156,
    "cbLTMultipleLOB": 159,
    "cbLTMultiplePosition": 150,
    "cbLTMultipleSubUnit": 147,
    "cbLTMultipleSupervisor": 165,
    "cbLTSearchMultipleLOB": 125,
    "cbLTSearchMultipleOmnia": 126,
    "cbOCEPBillability": 99,
    "cbOCEPBusUnit": 67,
    "cbOCEPCampaign": 76,
    "cbOCEPClient": 68,
    "cbOCEPCountry": 77,
    "cbOCEPEmpStatus": 98,
    "cbOCEPLOB": 84,
    "cbOCEPPosition": 83,
    "cbOCEPRole": 92,
    "cbOCEPSite": 85,
    "cbOCEPStatus": 93,
    "cbOCEPSubLOB": 91,
    "cbOCEPSubUnit": 75,
    "cbOCEPSupervisor": 69,
    "cbOCFPBillability": 606,
    "cbOCFPBusUnit": 610,
    "cbOCFPClient": 594,
    "cbOCFPCountry": 629,
    "cbOCFPDivision": 597,
    "cbOCFPEmpStatus": 622,
    "cbOCFPLOB": 600,
    "cbOCFPPosition": 616,
    "cbOCFPRole": 635,
    "cbOCFPSite": 632,
    "cbOCFPStatus": 619,
    "cbOCFPSubLOB": 603,
    "cbOCFPSubUnit": 613,
    "cbOCFPSupervisor": 626,
    "cbOTBillability": 224,
    "cbOTBusUnit": 194,
    "cbOTClient": 212,
    "cbOTLOB": 218,
    "cbOTOmnia": 179,
    "cbOTPosition": 206,
    "cbOTSearchLOB": 178,
    "cbOTStatus": 203,
    "cbOTSubUnit": 200,
    "cbOTSupervisor": 233,
    "cbPRMultipleBillability_1": 45,
    "cbPRMultipleBusUnit_1": 27,
    "cbPRMultipleClient_1": 39,
    "cbPRMultipleLOB_2": 42,
    "cbPRMultiplePosition_1": 33,
    "cbPRMultipleSubUnit_1": 30,
    "cbPRMultipleSupervisor_1": 48,
    "cbPRSearchMultipleLOB": 7,
    "cbPRSearchMultipleOmnia": 8,
    "class_name": 240,
    "Class_Name": 556,
    "CLASS_NAME": 239,
    "ClassName": 238,
    "CLIENT_Column1_1": 269,
    "CLIENT_DataCard PRMp1_1": 38,
    "CLIENT_DataCardOCFP": 592,
    "CLIENT_LTMDataCard": 155,
    "CLIENT_LTMDataCard2": 416,
    "CLIENT_OTDataCard": 211,
    "CLIENT_OTDataCard1": 529,
    "CLIENT_PRMDataCard2_2": 314,
    "comment_card": 490,
    "comment_card_1": 386,
    "comment_input": 492,
    "comment_input_1": 388,
    "comment_label": 491,
    "comment_label_1": 387,
    "COUNTRY_Column1_1": 273,
    "COUNTRY_DataCardOCFP": 627,
    "DataCard1": 431,
    "DataCard12": 620,
    "DataCard6": 326,
    "DataCard7": 413,
    "DataCard8": 595,
    "DataCard9": 630,
    "DataCardKey1": 400,
    "DataCardKey1_1": 509,
    "DataCardKey10": 585,
    "DataCardKey11": 588,
    "DataCardKey13": 222,
    "DataCardKey14": 228,
    "DataCardKey15_1": 612,
    "DataCardKey16_1": 615,
    "DataCardKey18": 539,
    "DataCardKey19": 545,
    "DataCardKey2": 160,
    "DataCardKey24": 138,
    "DataCardKey24_1": 191,
    "DataCardKey27": 521,
    "DataCardKey28": 527,
    "DataCardKey29": 533,
    "DataCardKey3": 43,
    "DataCardKey33": 593,
    "DataCardKey35": 602,
    "DataCardKey36": 408,
    "DataCardKey36_1": 518,
    "DataCardKey37": 145,
    "DataCardKey37_1": 405,
    "DataCardKey37_2": 195,
    "DataCardKey37_3": 512,
    "DataCardKey38": 148,
    "DataCardKey38_1": 201,
    "DataCardKey39": 157,
    "DataCardKey39_1": 213,
    "DataCardKey4": 420,
    "DataCardKey40": 163,
    "DataCardKey40_1": 225,
    "DataCardKey41": 151,
    "DataCardKey41_1": 207,
    "DataCardKey42": 166,
    "DataCardKey42_1": 234,
    "DataCardKey43_1": 231,
    "DataCardKey44": 411,
    "DataCardKey44_1": 524,
    "DataCardKey45": 417,
    "DataCardKey45_1": 530,
    "DataCardKey46": 599,
    "DataCardKey47": 141,
    "DataCardKey47_1": 402,
    "DataCardKey47_2": 197,
    "DataCardKey47_3": 515,
    "DataCardKey48": 605,
    "DataCardKey49": 625,
    "DataCardKey5": 219,
    "DataCardKey50": 423,
    "DataCardKey50_1": 542,
    "DataCardKey51_1": 548,
    "DataCardKey52_1": 551,
    "DataCardKey53": 628,
    "DataCardKey55": 634,
    "DataCardKey56": 576,
    "DataCardKey6": 579,
    "DataCardKey7": 536,
    "DataCardKey8": 318,
    "DataCardKey9": 582,
    "DataCardKeyBILLpm1_1": 46,
    "DataCardKeyBILLPRpm2_1": 322,
    "DataCardKeyBUpm1_1": 28,
    "DataCardKeyBUPRpm2_1": 303,
    "DataCardKeyCLpm1_1": 40,
    "DataCardKeyCLPRpm2_1": 315,
    "DataCardKeyENpm1_1": 21,
    "DataCardKeyENPRpm2_1": 297,
    "DataCardKeyPOSpm1_1": 34,
    "DataCardKeyPOSPRpm2_1": 310,
    "DataCardKeySITEpm1_1": 24,
    "DataCardKeySITEPRpm2_1": 300,
    "DataCardKeySUpm1_1": 31,
    "DataCardKeySUPpm1_1": 49,
    "DataCardKeySUPPRpm2_1": 324,
    "DataCardKeySUPRpm2_1": 307,
    "DataCardValue2": 421,
    "DataCardValue4": 319,
    "dateEnd": 215,
    "dateNesting": 221,
    "dateOCEPHireDate": 97,
    "dateOCFPHireDate": 589,
    "dateProduction": 227,
    "dateStart": 209,
    "dpLTEffectivityDate": 168,
    "dpPREffectivityDate": 51,
    "drpOTtimezone": 236,
    "drpRosterSelection": 338,
    "EFFECTIVITY_DATE": 50,
    "EFFECTIVITY_DATE_LT": 167,
    "effectivityDate_card": 481,
    "effectivityDate_card_1": 377,
    "effectivityDate_input": 483,
    "effectivityDate_input_1": 379,
    "effectivityDate_label": 482,
    "effectivityDate_label_1": 378,
    "EFFECTIVITYDATE_LT": 428,
    "email_card": 469,
    "email_card_1": 365,
    "email_label": 470,
    "email_label_1": 367,
    "email_value": 471,
    "email_value_1": 366,
    "EMPLOYEE ID_Column1_1": 261,
    "EMPLOYEE ID_DataCard1": 398,
    "EMPLOYEE ID_DataCardOCFP": 575,
    "EMPLOYEE ID_LTMDataCard": 137,
    "EMPLOYEE ID_OTDataCard": 190,
    "EMPLOYEE ID_OTDataCard1": 508,
    "EMPLOYEE NAME_PRMDataCard_3": 296,
    "EmployeeGallery": 449,
    "EmployeeGallery_1": 345,
    "employeeID": 454,
    "employeeID_1": 350,
    "EmployeeInfo_form": 456,
    "EmployeeInfo_form_1": 352,
    "employeeInfo_label": 448,
    "employeeInfo_label_1": 344,
    "employeeList_label": 447,
    "employeeList_label_1": 343,
    "employeeName": 451,
    "employeeName_1": 347,
    "EMPLOYMENT STATUS_Column1": 277,
    "END DATE_OTDataCard": 214,
    "END DATE_OTDataCard1": 532,
    "FIRST NAME_Column1_1": 262,
    "FIRST NAME_DataCardOCFP": 578,
    "fname_card": 457,
    "fname_card_1": 353,
    "fname_label": 458,
    "fname_label_1": 354,
    "fname_value": 459,
    "fname_value_1": 355,
    "formLTM": 136,
    "formLTM2": 397,
    "formOCFirstPage1": 574,
    "formOCFirstPage2": 607,
    "formOCFirstPage3": 591,
    "formOCFirstPage4": 623,
    "formOT": 189,
    "formOT1": 507,
    "formPREDsp2": 19,
    "formPREDsp2_1": 295,
    "FULL NAME_DataCard PRMp1_1": 20,
    "galleryLTM": 130,
    "galleryLTM_1": 433,
    "galleryLTM_2": 501,
    "galleryOT": 183,
    "galleryPRMp1st_1": 12,
    "galleryPRMp2nd_1": 289,
    "galleryTemplate2": 131,
    "galleryTemplate2_1": 434,
    "galleryTemplate2_2": 184,
    "galleryTemplate2_3": 502,
    "galleryTemplate2_4": 13,
    "galleryTemplate2_5": 290,
    "galleryTemplate3": 450,
    "galleryTemplate3_1": 346,
    "galleryTemplate6": 61,
    "galOCEP": 60,
    "grpLTSearchMultipleLOB": 174,
    "grpLTSearchMultipleOmnia": 173,
    "grpNewOCForm": 640,
    "grpOCECountry": 115,
    "grpOCEPBillability": 118,
    "grpOCEPBusUnit": 106,
    "grpOCEPButtons": 121,
    "grpOCEPCampaign": 111,
    "grpOCEPClient": 110,
    "grpOCEPEmpId": 100,
    "grpOCEPEmpStatus": 109,
    "grpOCEPFName": 101,
    "grpOCEPHireDate": 104,
    "grpOCEPLName": 103,
    "grpOCEPLOB": 112,
    "grpOCEPMName": 102,
    "grpOCEPPosition": 108,
    "grpOCEPRole": 117,
    "grpOCEPSite": 116,
    "grpOCEPStatus": 105,
    "grpOCEPSubLOB": 113,
    "grpOCEPSubUnit": 107,
    "grpOCEPSupervisor": 114,
    "grpOCFPButtons": 641,
    "grpOCSPActions": 283,
    "grpOCSPButtons": 284,
    "grpOTLOB": 255,
    "grpOTOmnia": 254,
    "grpPRSearchMultipleLOB_1": 57,
    "grpPRSearchMultipleOmnia_1": 56,
    "HIRE DATE_Column1_1": 265,
    "HIRE DATE_DataCardOCFP": 587,
    "HomePage": 333,
    "Host": 3,
    "INTERNAL EMAIL": 648,
    "INTERNSHIP_DataCard": 35,
    "INTERNSHIP_DataCard_2": 311,
    "INTERNSHIP_LTMDataCard": 152,
    "Label1": 373,
    "Label10": 249,
    "Label11": 313,
    "Label12": 312,
    "Label13": 153,
    "Label14": 557,
    "Label15": 415,
    "Label16": 414,
    "Label17": 560,
    "Label18": 237,
    "Label19": 335,
    "Label2": 204,
    "Label20": 554,
    "Label21": 555,
    "Label22": 596,
    "Label23": 337,
    "Label24": 631,
    "Label25": 609,
    "Label26": 563,
    "Label27": 618,
    "Label28": 566,
    "Label29": 621,
    "Label3": 210,
    "Label30": 561,
    "Label31": 567,
    "Label32": 558,
    "Label33": 564,
    "Label34": 429,
    "Label35": 430,
    "Label36": 426,
    "Label37": 649,
    "Label38": 427,
    "Label39": 52,
    "Label4": 216,
    "Label40": 327,
    "Label41": 328,
    "Label5": 62,
    "Label5_1": 70,
    "Label5_10": 64,
    "Label5_11": 72,
    "Label5_12": 80,
    "Label5_13": 87,
    "Label5_14": 65,
    "Label5_15": 73,
    "Label5_16": 81,
    "Label5_17": 88,
    "Label5_18": 96,
    "Label5_2": 78,
    "Label5_3": 86,
    "Label5_4": 94,
    "Label5_5": 63,
    "Label5_6": 71,
    "Label5_7": 79,
    "Label5_8": 95,
    "Label5_9": 89,
    "Label6": 169,
    "Label7": 36,
    "Label8": 242,
    "Label9": 246,
    "LAST NAME_Column1_1": 264,
    "LAST NAME_DataCardOCFP": 584,
    "lastDate_card": 484,
    "lastDate_card_1": 380,
    "lastDate_input": 486,
    "lastDate_input_1": 382,
    "lastDate_label": 485,
    "lastDate_label_1": 381,
    "Lateral Transfer Form_1": 123,
    "Lateral Transfer Form_2": 128,
    "Lateral Transfer Form_3": 129,
    "Lateral Transfer Form_4": 394,
    "Lateral Transfer Form_5": 395,
    "Lateral Transfer Form_6": 396,
    "LateralTransfer_FirstPage": 122,
    "LateralTransfer_SecondPage": 393,
    "LineOfBusiness_Label_1": 445,
    "lname_card": 460,
    "lname_card_1": 356,
    "lname_label": 461,
    "lname_label_1": 358,
    "lname_value": 462,
    "lname_value_1": 357,
    "lob_card": 466,
    "lob_card_1": 362,
    "LOB_Column1_1": 271,
    "LOB_DataCard1": 158,
    "LOB_DataCard2": 41,
    "LOB_DataCard3": 419,
    "LOB_DataCard4": 217,
    "LOB_DataCard7": 317,
    "LOB_DataCardOCFP": 598,
    "lob_input": 444,
    "lob_label": 467,
    "lob_Label": 443,
    "lob_label_1": 364,
    "LOB_OTDataCard1": 535,
    "lob_value": 468,
    "lob_value_1": 363,
    "MIDDLE NAME_Column1_1": 263,
    "MIDDLE NAME_DataCardOCFP": 581,
    "MultipleTerminationForm_Label": 442,
    "MultipleTerminationForm_Label_1": 342,
    "NESTING START DATE_DataCard1": 220,
    "NESTING START DATE_DataCard3": 538,
    "NextArrow2": 133,
    "NextArrow2_1": 186,
    "NextArrow2_1_Verify_1": 15,
    "NextArrow3": 436,
    "NextArrow3_1": 504,
    "NextArrow4": 452,
    "NextArrow4_2": 348,
    "NextArrow4_2_Verify_1": 292,
    "oc1": 573,
    "oc2": 257,
    "oc3": 59,
    "omnia_input": 446,
    "OmniaCreation_EditPage": 58,
    "OmniaCreation_FirstPage": 572,
    "OmniaCreation_SecondPage": 256,
    "omniaID": 453,
    "omniaID_1": 349,
    "OT1": 176,
    "OT2": 181,
    "OT3": 182,
    "OT4": 500,
    "OT5": 499,
    "OT6": 498,
    "Others_FirstPage": 175,
    "Others_SecondPage": 497,
    "position_card": 463,
    "position_card_1": 359,
    "POSITION_Column1_1": 268,
    "POSITION_DataCard PRMp1_1": 32,
    "POSITION_DataCardOCFP": 614,
    "position_label": 464,
    "position_label_1": 360,
    "POSITION_LTMDataCard": 149,
    "POSITION_LTMDataCard2": 410,
    "POSITION_OTDataCard": 205,
    "POSITION_OTDataCard1": 523,
    "POSITION_PRMDataCard2_2": 308,
    "position_value": 465,
    "position_value_1": 361,
    "proceed_btn": 496,
    "proceed_btn_1": 392,
    "PRODUCTION DATE_DataCard1": 226,
    "PRODUCTION DATE_DataCard3": 544,
    "Promotion Form p2_1": 286,
    "Promotion Form_1": 5,
    "Promotion_FirstPage": 4,
    "Promotion_SecondPage": 285,
    "rdLTMInternship": 154,
    "rdPRInternship": 37,
    "Rectangle1": 643,
    "Rectangle2": 334,
    "REGULARIZATION DATE_Column1": 275,
    "Reminder": 340,
    "Remove Button Container": 389,
    "Remove_Button": 329,
    "REMOVE_BUTTON": 568,
    "ROLE_Column1_1": 274,
    "ROLE_DataCardOCFP": 633,
    "Roster Update Selection": 336,
    "Save Button Container": 493,
    "Save_Button": 250,
    "SCHEDULE_OTDataCard": 229,
    "SCHEDULE_OTDataCard1": 547,
    "Separator2": 135,
    "Separator2_1": 188,
    "Separator2_1_Verify_1": 18,
    "Separator3": 438,
    "Separator3_1": 506,
    "Separator4": 455,
    "Separator4_2": 351,
    "Separator4_2_Verify_1": 294,
    "SITE DataCard PRMp1_1": 23,
    "SITE_Column1_1": 280,
    "SITE_LTMDataCard": 140,
    "SITE_LTMDataCard2": 401,
    "SITE_OTDataCard": 196,
    "SITE_OTDataCard1": 514,
    "SITE_PRMDataCard_4": 299,
    "START DATE_OTDataCard": 208,
    "START DATE_OTDataCard1": 526,
    "STATUS_Column1": 276,
    "STATUS_DataCardOCFP": 617,
    "STATUS_OTDataCard": 202,
    "STATUS_OTDataCard1": 520,
    "SUB UNIT_Column1_1": 267,
    "SUB-LOB_Column1_1": 278,
    "SUB-LOB_DataCardOCFP": 601,
    "SUB-UNIT_DataCard PRMp1_1": 29,
    "SUB-UNIT_DataCardOCFP": 611,
    "SUB-UNIT_LTMDataCard": 146,
    "SUB-UNIT_LTMDataCard2": 407,
    "SUB-UNIT_OTDataCard": 199,
    "SUB-UNIT_OTDataCard1": 517,
    "SUB-UNIT_PRMDataCard2_2": 305,
    "SUPERVISOR_Column1_1": 279,
    "SUPERVISOR_DataCard PRMp1_1": 47,
    "SUPERVISOR_LT": 425,
    "SUPERVISOR_LTMDataCard": 164,
    "SUPERVISOR_OTDataCard": 232,
    "SUPERVISOR_OTDataCard1": 550,
    "tblOCSP": 260,
    "TEAM_DataCardOCFP": 624,
    "TEAM_PRMDataCard2_2": 323,
    "Termination Status Verify": 376,
    "Termination_FirstPage": 441,
    "Termination_VerificationPage": 341,
    "terminationStatus_card": 478,
    "terminationStatus_card_1": 374,
    "terminationStatus_cb": 480,
    "terminationStatus_label": 479,
    "terminationStatus_label_1": 375,
    "terminationType_card": 475,
    "terminationType_card_1": 371,
    "terminationType_cb": 477,
    "terminationType_label": 476,
    "terminationType_label_1": 372,
    "Time_Zone": 235,
    "TIME_ZONE": 553,
    "trainer1": 243,
    "Trainer1": 559,
    "TRAINER1": 241,
    "trainer2": 245,
    "Trainer2": 562,
    "TRAINER2": 244,
    "trainer3": 248,
    "Trainer3": 565,
    "TRAINER3": 247,
    "txtLTMultipleBillability2": 424,
    "txtLTMultipleBusUnit2": 406,
    "txtLTMultipleEmpId": 139,
    "txtLTMultipleEmpId2": 399,
    "txtLTMultipleName": 132,
    "txtLTMultipleName_1": 435,
    "txtLTMultipleName_2": 503,
    "txtLTMultipleName_3": 291,
    "txtLTMultipleOmnia": 134,
    "txtLTMultipleOmnia_1": 437,
    "txtLTMultipleOmnia_2": 505,
    "txtLTMultiplePosition2": 412,
    "txtLTMultipleSite": 142,
    "txtLTMultipleSite2": 403,
    "txtLTMultipleSubUnit2": 409,
    "txtLTMutipleClient2": 418,
    "txtLTSearchMultipleLOB": 124,
    "txtLTSearchMultipleOmnia": 127,
    "txtOCEPEmpId": 66,
    "txtOCEPFName": 74,
    "txtOCEPLName": 90,
    "txtOCEPMName": 82,
    "txtOCFPEmpId": 577,
    "txtOCFPFName": 580,
    "txtOCFPLName": 586,
    "txtOCFPMName": 583,
    "txtOCInternalEmail": 650,
    "txtOTBillability1": 543,
    "txtOTBusUnit1": 513,
    "txtOTClient1": 531,
    "txtOTEmpId": 192,
    "txtOTEmpId1": 510,
    "txtOTEndDate1": 534,
    "txtOTLOB": 177,
    "txtOTLOB1": 537,
    "txtOTMName": 185,
    "txtOTMOmnia": 187,
    "txtOTNesting1": 540,
    "txtOTOmnia": 180,
    "txtOTPosition1": 525,
    "txtOTProduction1": 546,
    "txtOTSchedule": 230,
    "txtOTSchedule1": 549,
    "txtOTSite": 198,
    "txtOTSite1": 516,
    "txtOTStartdate1": 528,
    "txtOTStatus1": 522,
    "txtOTSubUnit1": 519,
    "txtOTSupervisor1": 552,
    "txtPREDp1_1": 11,
    "txtPREDp2_1": 288,
    "txtPRMultipleBILLpm2_1": 321,
    "txtPRMultipleBUpm2_1": 304,
    "txtPRMultipleCLpm2_1": 316,
    "txtPRMultipleEmpName_1": 22,
    "txtPRMultipleEmpNamepm2_1": 298,
    "txtPRMultipleIdpm1_1": 16,
    "txtPRMultipleNamepm1_1": 14,
    "txtPRMultipleOmniapm1_1": 17,
    "txtPRMultipleOmniapm2_1": 293,
    "txtPRMultiplePOSpm2_1": 309,
    "txtPRMultipleSite_1": 25,
    "txtPRMultipleSitepm2_1": 301,
    "txtPRMultipleSUpm2_1": 306,
    "txtPRMultipleSUPpm2_1": 325,
    "txtPRSearchMultipleLOB_1": 6,
    "txtPRSearchMultipleOmnia_1": 9,
    "txtPRSEp1_1": 10,
    "txtPRUEp2_1": 287
  },
  "FunctionParamsInvariantScripts": {},
  "FunctionParamsInvariantScriptsOnInstances": {},
  "HeaderLastSavedDateTimeUTC": "09/14/2023 17:57:42",
  "IsLegacyComponentAllowGlobalScopeCase": false,
  "LocalConnectionIDReferences": {
    "09c7e83f-c277-4a47-9c32-0abf82fd71e0": "\"/providers/microsoft.powerapps/apis/shared_logicflows/connections/46ddec93-817d-4eef-bd60-2d2a6c960d36\"",
    "0d6d0b4d-fac7-40bc-8729-e33df6d6fdef": "\"/providers/microsoft.powerapps/apis/shared_logicflows/connections/9e4fe233-8209-49cc-816e-4394bf7c6250\"",
    "13dcac71-2ab7-453b-9716-c8e0ca02d7fd": "\"/providers/microsoft.powerapps/apis/shared_logicflows/connections/bffd45e5-c510-41f6-b7e9-e0c1a0a2ea91\"",
    "289879e3-07d6-4fd1-9930-da8bc0582571": "\"/providers/microsoft.powerapps/apis/shared_logicflows/connections/1080521d-b001-4571-ad84-344fa9e9019a\"",
    "38558032-7fd8-4634-9a2b-513f72a8e807": "\"/providers/microsoft.powerapps/apis/shared_logicflows/connections/656f47b763aa4718adf40beffb206926-ed4dc2137967c9c7\"",
    "445c2806-6ace-410f-adcf-5edfa6f6c6cb": "\"/providers/microsoft.powerapps/apis/shared_excelonlinebusiness/connections/8b6be7bedfa041b09a54cd206cb1acd0\"",
    "4d5255a7-ad0e-49cb-a2b7-8210242f9577": "\"/providers/microsoft.powerapps/apis/shared_office365/connections/shared-office365-294c685d-60f7-42af-8603-e6fb83585655\"",
    "5e32bcde-a6f7-4fb1-b485-eb17650fc98d": "\"/providers/microsoft.powerapps/apis/shared_sharepointonline/connections/b68326d57523434ca0341d6f0cbd62bb\"",
    "67bcd3c5-be60-4c7f-b0c8-7c3a20de6d4a": "\"/providers/microsoft.powerapps/apis/shared_logicflows/connections/1ee8f94d83a14c9691fcd1c9d74d2686\"",
    "9ff01be1-b3e1-455f-a660-7b5ae6d360db": "\"/providers/microsoft.powerapps/apis/shared_logicflows/connections/a18c19a5-5014-4f6a-a8fb-834c3cb0b104\"",
    "a98f1ce0-65af-4442-ad24-7697c24f3724": "\"/providers/microsoft.powerapps/apis/shared_office365/connections/shared-office365-294c685d-60f7-42af-8603-e6fb83585655\"",
    "bc5a7c8b-3b68-4abd-b0aa-771a79eeae2c": "\"/providers/microsoft.powerapps/apis/shared_office365/connections/shared-office365-294c685d-60f7-42af-8603-e6fb83585655\"",
    "d5946ca7-4730-4a79-9df6-a4ac4166d737": "\"/providers/microsoft.powerapps/apis/shared_logicflows/connections/b922a241-3511-4bda-93da-2636223705df\"",
    "db0139ba-0e04-406c-9575-fc570ff1f5a7": "\"/providers/microsoft.powerapps/apis/shared_logicflows/connections/718c6e7107c748b595aef3c3ac427b8f\"",
    "fc828f20-0077-422d-866a-280908c1e74e": "\"/providers/microsoft.powerapps/apis/shared_logicflows/connections/be732a28-3927-4a2e-85c5-723dabcff42b\""
  },
  "LocalDatabaseReferencesAsEmpty": false,
  "LocalResourceFileNames": {
    "homeScreen": "83ae0a84-050f-4954-af53-4824d9d7e624.png",
    "homeScreen2": "f3221eef-2964-4bea-bdec-75bd42bdf521.png",
    "MicrosoftTeams-image": "7886b3c1-9983-4892-a2e5-cec6afa3fa41.png",
    "MicrosoftTeams-image (2)": "f781a3c3-d213-4099-acf4-9844bd2d1c6a.png",
    "Untitled design 29": "978392d2-fc92-4e8f-a15e-6aa4c499d7d4.png"
  },
  "LocalResourceRootPaths": {
    "homeScreen": "https://docserverpwaprodwus.blob.core.windows.net/b8f42995-4abb-4633-8606-1cd38380071e-1/resource/Assets0Images083ae0a84-050f-4954-af53-4824d9d7e624.png?sv=2018-03-28&sr=b&sig=26dySERSq8PiNg9Q27dOX5ce1KmIR0NuRoPk8feHQ%2Bs%3D&spr=https&se=2023-09-15T14%3A40%3A20Z&sp=r",
    "homeScreen2": "https://docserverpwaprodwus.blob.core.windows.net/b8f42995-4abb-4633-8606-1cd38380071e-1/resource/Assets0Images0f3221eef-2964-4bea-bdec-75bd42bdf521.png?sv=2018-03-28&sr=b&sig=5SvPkWE%2BNjRVZY%2F6kewYFOZ9bK%2FlnKEx3oRYdq5uNNY%3D&spr=https&se=2023-09-15T14%3A40%3A20Z&sp=r",
    "MicrosoftTeams-image": "https://docserverpwaprodwus.blob.core.windows.net/b8f42995-4abb-4633-8606-1cd38380071e-1/resource/Assets0Images07886b3c1-9983-4892-a2e5-cec6afa3fa41.png?sv=2018-03-28&sr=b&sig=bnYMGj%2FH5dfrXVrhb1Et%2ByZlJ5gQSypulerQUI9HhNY%3D&spr=https&se=2023-09-15T14%3A40%3A20Z&sp=r",
    "MicrosoftTeams-image (2)": "https://docserverpwaprodwus.blob.core.windows.net/b8f42995-4abb-4633-8606-1cd38380071e-1/resource/Assets0Images0f781a3c3-d213-4099-acf4-9844bd2d1c6a.png?sv=2018-03-28&sr=b&sig=BYRM0qr6cBDwCsudYf%2FrxLEulpV%2BYFE%2F9eZo8yfY5W4%3D&spr=https&se=2023-09-15T14%3A40%3A20Z&sp=r",
    "Untitled design 29": "https://docserverpwaprodwus.blob.core.windows.net/b8f42995-4abb-4633-8606-1cd38380071e-1/resource/Assets0Images0978392d2-fc92-4e8f-a15e-6aa4c499d7d4.png?sv=2018-03-28&sr=b&sig=uCA9gzlBiRQkn8q74Mj4VRy9rtUVzmpCvcpW%2B4Ahsxo%3D&spr=https&se=2023-09-15T14%3A40%3A20Z&sp=r"
  },
  "OldLogoFileName": "mlxmmrgs.jpg",
  "OrderComponentMetadata": {},
  "OrderComponentTemplate": {},
  "OrderDataSource": {
    "coldata": 19,
    "colLateralTransfer": 16,
    "colOmniaCreation": 22,
    "colOthers": 17,
    "colPromotion": 20,
    "colPromotion1": 21,
    "ComboBoxSample": 11,
    "CustomGallerySample": 12,
    "DropDownSample": 13,
    "Headcount_table": 15,
    "Office365Outlook": 0,
    "RadioSample": 14,
    "Request-LateralTransfer_1": 9,
    "Request-Promotion_1": 10,
    "SubmitLateralTransfer": 5,
    "SubmitOmniaCreation": 3,
    "SubmitOtherRosterUpdate": 1,
    "SubmitPromotion": 4,
    "SubmitTermination": 2,
    "TestSubmitOmniaCreation": 8,
    "TestSubmitPromotion": 7,
    "TestSubmitTermination": 6,
    "userVerify": 18
  },
  "OrderGroupControls": {
    "grpLTSearchMultipleLOB": {
      "cbLTSearchMultipleLOB": 1,
      "txtLTSearchMultipleLOB": 0
    },
    "grpLTSearchMultipleOmnia": {
      "cbLTSearchMultipleOmnia": 0,
      "txtLTSearchMultipleOmnia": 1
    },
    "grpNewOCForm": {
      "formOCFirstPage1": 3,
      "formOCFirstPage2": 2,
      "formOCFirstPage3": 1,
      "formOCFirstPage4": 0
    },
    "grpOCECountry": {
      "cbOCEPCountry": 0,
      "Label5_15": 1
    },
    "grpOCEPBillability": {
      "cbOCEPBillability": 1,
      "Label5_18": 0
    },
    "grpOCEPBusUnit": {
      "cbOCEPBusUnit": 0,
      "Label5_5": 1
    },
    "grpOCEPButtons": {
      "btnOCEPBack": 0,
      "btnOCEPUpdate": 1
    },
    "grpOCEPCampaign": {
      "cbOCEPCampaign": 0,
      "Label5_11": 1
    },
    "grpOCEPClient": {
      "cbOCEPClient": 0,
      "Label5_10": 1
    },
    "grpOCEPEmpId": {
      "Label5": 1,
      "txtOCEPEmpId": 0
    },
    "grpOCEPEmpStatus": {
      "cbOCEPEmpStatus": 1,
      "Label5_8": 0
    },
    "grpOCEPFName": {
      "Label5_1": 1,
      "txtOCEPFName": 0
    },
    "grpOCEPHireDate": {
      "dateOCEPHireDate": 1,
      "Label5_4": 0
    },
    "grpOCEPLName": {
      "Label5_3": 0,
      "txtOCEPLName": 1
    },
    "grpOCEPLOB": {
      "cbOCEPLOB": 0,
      "Label5_12": 1
    },
    "grpOCEPMName": {
      "Label5_2": 0,
      "txtOCEPMName": 1
    },
    "grpOCEPPosition": {
      "cbOCEPPosition": 0,
      "Label5_7": 1
    },
    "grpOCEPRole": {
      "cbOCEPRole": 1,
      "Label5_17": 0
    },
    "grpOCEPSite": {
      "cbOCEPSite": 0,
      "Label5_16": 1
    },
    "grpOCEPStatus": {
      "cbOCEPStatus": 0,
      "Label5_9": 1
    },
    "grpOCEPSubLOB": {
      "cbOCEPSubLOB": 1,
      "Label5_13": 0
    },
    "grpOCEPSubUnit": {
      "cbOCEPSubUnit": 0,
      "Label5_6": 1
    },
    "grpOCEPSupervisor": {
      "cbOCEPSupervisor": 0,
      "Label5_14": 1
    },
    "grpOCFPButtons": {
      "btnOCFPBack": 0,
      "btnOCFPReview": 1
    },
    "grpOCSPActions": {
      "btnOCSPEdit": 0,
      "btnOCSPRemove": 1
    },
    "grpOCSPButtons": {
      "btnOCSPBack": 0,
      "btnOCSPSubmit": 1
    },
    "grpOTLOB": {
      "cbOTSearchLOB": 1,
      "txtOTLOB": 0
    },
    "grpOTOmnia": {
      "cbOTOmnia": 0,
      "txtOTOmnia": 1
    },
    "grpPRSearchMultipleLOB_1": {
      "cbPRSearchMultipleLOB": 1,
      "txtPRSearchMultipleLOB_1": 0
    },
    "grpPRSearchMultipleOmnia_1": {
      "cbPRSearchMultipleOmnia": 0,
      "txtPRSearchMultipleOmnia_1": 1
    },
    "Reminder": {
      "Label19": 0,
      "Label23": 1,
      "Rectangle2": 2
    }
  },
  "OrderPcfTemplate": {},
  "OrderTemplate": {},
  "OrderXMLTemplate": {
    "button": 8,
    "combobox": 1,
    "datepicker": 7,
    "dropdown": 10,
    "form": 5,
    "gallery": 2,
    "htmlViewer": 11,
    "icon": 3,
    "label": 0,
    "radio": 6,
    "rectangle": 4,
    "text": 9
  },
  "OverridablePropertiesEntry": {
    "address_card": {},
    "address_card_1": {},
    "address_input": {},
    "address_input_1": {},
    "address_label": {},
    "address_label_1": {},
    "App": {},
    "BILLABILITY_Column1_1": {},
    "BILLABILITY_DataCard PRMp1_1": {},
    "BILLABILITY_DataCardOCFP": {},
    "BILLABILITY_LTMDataCard": {},
    "BILLABILITY_LTMDataCard2": {},
    "BILLABILITY_OTDataCard": {},
    "BILLABILITY_OTDataCard1": {},
    "BILLABILITY_PRMDataCard2_2": {},
    "btnFirstPageNext": {},
    "btnLTMultipleBack": {},
    "btnLTMultipleBack_1": {},
    "btnLTMultipleBack_2": {},
    "btnLTMultipleBack_3": {},
    "btnLTMultipleBack_4": {},
    "btnLTMultipleReview": {},
    "btnLTMultipleReview_1": {},
    "btnLTMultipleReview_2": {},
    "btnLTRemove": {},
    "btnLTRemove_1": {},
    "btnOCEPBack": {},
    "btnOCEPUpdate": {},
    "btnOCFPBack": {},
    "btnOCFPReview": {},
    "btnOCFPSave": {},
    "btnOCSPBack": {},
    "btnOCSPEdit": {},
    "btnOCSPRemove": {},
    "btnOCSPSubmit": {},
    "btnOTBack": {},
    "btnOTRemove": {},
    "btnOTReview": {},
    "btnOTSave": {},
    "btnPRMultipleBackp1_1": {},
    "btnPRMultipleBackp2_1": {},
    "btnPRMultipleReviewp1_1": {},
    "btnPRMultipleSubmitp2_1": {},
    "btnPRRemovep2_3": {},
    "BUSINESS UNIT_Column1_1": {},
    "BUSINESS UNIT_DataCard PRMp1_1": {},
    "BUSINESS UNIT_DataCardOCFP": {},
    "BUSINESS UNIT_LTMDataCard": {},
    "BUSINESS UNIT_LTMDataCard2": {},
    "BUSINESS UNIT_OTDataCard": {},
    "BUSINESS UNIT_OTDataCard1": {},
    "BUSINESS UNIT_PRMDataCard_4": {},
    "Button1": {},
    "Button2": {},
    "Button3": {},
    "Button4": {},
    "campaign_card": {},
    "campaign_card_1": {},
    "CAMPAIGN_Column1_1": {},
    "campaign_label": {},
    "campaign_label_1": {},
    "campaign_value": {},
    "campaign_value_1": {},
    "cbLTMultipleBillability": {},
    "cbLTMultipleBusUnit": {},
    "cbLTMultipleClient": {},
    "cbLTMultipleLOB": {},
    "cbLTMultiplePosition": {},
    "cbLTMultipleSubUnit": {},
    "cbLTMultipleSupervisor": {},
    "cbLTSearchMultipleLOB": {},
    "cbLTSearchMultipleOmnia": {},
    "cbOCEPBillability": {},
    "cbOCEPBusUnit": {},
    "cbOCEPCampaign": {},
    "cbOCEPClient": {},
    "cbOCEPCountry": {},
    "cbOCEPEmpStatus": {},
    "cbOCEPLOB": {},
    "cbOCEPPosition": {},
    "cbOCEPRole": {},
    "cbOCEPSite": {},
    "cbOCEPStatus": {},
    "cbOCEPSubLOB": {},
    "cbOCEPSubUnit": {},
    "cbOCEPSupervisor": {},
    "cbOCFPBillability": {},
    "cbOCFPBusUnit": {},
    "cbOCFPClient": {},
    "cbOCFPCountry": {},
    "cbOCFPDivision": {},
    "cbOCFPEmpStatus": {},
    "cbOCFPLOB": {},
    "cbOCFPPosition": {},
    "cbOCFPRole": {},
    "cbOCFPSite": {},
    "cbOCFPStatus": {},
    "cbOCFPSubLOB": {},
    "cbOCFPSubUnit": {},
    "cbOCFPSupervisor": {},
    "cbOTBillability": {},
    "cbOTBusUnit": {},
    "cbOTClient": {},
    "cbOTLOB": {},
    "cbOTOmnia": {},
    "cbOTPosition": {},
    "cbOTSearchLOB": {},
    "cbOTStatus": {},
    "cbOTSubUnit": {},
    "cbOTSupervisor": {},
    "cbPRMultipleBillability_1": {},
    "cbPRMultipleBusUnit_1": {},
    "cbPRMultipleClient_1": {},
    "cbPRMultipleLOB_2": {},
    "cbPRMultiplePosition_1": {},
    "cbPRMultipleSubUnit_1": {},
    "cbPRMultipleSupervisor_1": {},
    "cbPRSearchMultipleLOB": {},
    "cbPRSearchMultipleOmnia": {},
    "class_name": {},
    "Class_Name": {},
    "CLASS_NAME": {},
    "ClassName": {},
    "CLIENT_Column1_1": {},
    "CLIENT_DataCard PRMp1_1": {},
    "CLIENT_DataCardOCFP": {},
    "CLIENT_LTMDataCard": {},
    "CLIENT_LTMDataCard2": {},
    "CLIENT_OTDataCard": {},
    "CLIENT_OTDataCard1": {},
    "CLIENT_PRMDataCard2_2": {},
    "comment_card": {},
    "comment_card_1": {},
    "comment_input": {},
    "comment_input_1": {},
    "comment_label": {},
    "comment_label_1": {},
    "COUNTRY_Column1_1": {},
    "COUNTRY_DataCardOCFP": {},
    "DataCard1": {},
    "DataCard12": {},
    "DataCard6": {},
    "DataCard7": {},
    "DataCard8": {},
    "DataCard9": {},
    "DataCardKey1": {},
    "DataCardKey1_1": {},
    "DataCardKey10": {},
    "DataCardKey11": {},
    "DataCardKey13": {},
    "DataCardKey14": {},
    "DataCardKey15_1": {},
    "DataCardKey16_1": {},
    "DataCardKey18": {},
    "DataCardKey19": {},
    "DataCardKey2": {},
    "DataCardKey24": {},
    "DataCardKey24_1": {},
    "DataCardKey27": {},
    "DataCardKey28": {},
    "DataCardKey29": {},
    "DataCardKey3": {},
    "DataCardKey33": {},
    "DataCardKey35": {},
    "DataCardKey36": {},
    "DataCardKey36_1": {},
    "DataCardKey37": {},
    "DataCardKey37_1": {},
    "DataCardKey37_2": {},
    "DataCardKey37_3": {},
    "DataCardKey38": {},
    "DataCardKey38_1": {},
    "DataCardKey39": {},
    "DataCardKey39_1": {},
    "DataCardKey4": {},
    "DataCardKey40": {},
    "DataCardKey40_1": {},
    "DataCardKey41": {},
    "DataCardKey41_1": {},
    "DataCardKey42": {},
    "DataCardKey42_1": {},
    "DataCardKey43_1": {},
    "DataCardKey44": {},
    "DataCardKey44_1": {},
    "DataCardKey45": {},
    "DataCardKey45_1": {},
    "DataCardKey46": {},
    "DataCardKey47": {},
    "DataCardKey47_1": {},
    "DataCardKey47_2": {},
    "DataCardKey47_3": {},
    "DataCardKey48": {},
    "DataCardKey49": {},
    "DataCardKey5": {},
    "DataCardKey50": {},
    "DataCardKey50_1": {},
    "DataCardKey51_1": {},
    "DataCardKey52_1": {},
    "DataCardKey53": {},
    "DataCardKey55": {},
    "DataCardKey56": {},
    "DataCardKey6": {},
    "DataCardKey7": {},
    "DataCardKey8": {},
    "DataCardKey9": {},
    "DataCardKeyBILLpm1_1": {},
    "DataCardKeyBILLPRpm2_1": {},
    "DataCardKeyBUpm1_1": {},
    "DataCardKeyBUPRpm2_1": {},
    "DataCardKeyCLpm1_1": {},
    "DataCardKeyCLPRpm2_1": {},
    "DataCardKeyENpm1_1": {},
    "DataCardKeyENPRpm2_1": {},
    "DataCardKeyPOSpm1_1": {},
    "DataCardKeyPOSPRpm2_1": {},
    "DataCardKeySITEpm1_1": {},
    "DataCardKeySITEPRpm2_1": {},
    "DataCardKeySUpm1_1": {},
    "DataCardKeySUPpm1_1": {},
    "DataCardKeySUPPRpm2_1": {},
    "DataCardKeySUPRpm2_1": {},
    "DataCardValue2": {},
    "DataCardValue4": {},
    "dateEnd": {},
    "dateNesting": {},
    "dateOCEPHireDate": {},
    "dateOCFPHireDate": {},
    "dateProduction": {},
    "dateStart": {},
    "dpLTEffectivityDate": {},
    "dpPREffectivityDate": {},
    "drpOTtimezone": {},
    "drpRosterSelection": {},
    "EFFECTIVITY_DATE": {},
    "EFFECTIVITY_DATE_LT": {},
    "effectivityDate_card": {},
    "effectivityDate_card_1": {},
    "effectivityDate_input": {},
    "effectivityDate_input_1": {},
    "effectivityDate_label": {},
    "effectivityDate_label_1": {},
    "EFFECTIVITYDATE_LT": {},
    "email_card": {},
    "email_card_1": {},
    "email_label": {},
    "email_label_1": {},
    "email_value": {},
    "email_value_1": {},
    "EMPLOYEE ID_Column1_1": {},
    "EMPLOYEE ID_DataCard1": {},
    "EMPLOYEE ID_DataCardOCFP": {},
    "EMPLOYEE ID_LTMDataCard": {},
    "EMPLOYEE ID_OTDataCard": {},
    "EMPLOYEE ID_OTDataCard1": {},
    "EMPLOYEE NAME_PRMDataCard_3": {},
    "EmployeeGallery": {},
    "EmployeeGallery_1": {},
    "employeeID": {},
    "employeeID_1": {},
    "EmployeeInfo_form": {},
    "EmployeeInfo_form_1": {},
    "employeeInfo_label": {},
    "employeeInfo_label_1": {},
    "employeeList_label": {},
    "employeeList_label_1": {},
    "employeeName": {},
    "employeeName_1": {},
    "EMPLOYMENT STATUS_Column1": {},
    "END DATE_OTDataCard": {},
    "END DATE_OTDataCard1": {},
    "FIRST NAME_Column1_1": {},
    "FIRST NAME_DataCardOCFP": {},
    "fname_card": {},
    "fname_card_1": {},
    "fname_label": {},
    "fname_label_1": {},
    "fname_value": {},
    "fname_value_1": {},
    "formLTM": {},
    "formLTM2": {},
    "formOCFirstPage1": {},
    "formOCFirstPage2": {},
    "formOCFirstPage3": {},
    "formOCFirstPage4": {},
    "formOT": {},
    "formOT1": {},
    "formPREDsp2": {},
    "formPREDsp2_1": {},
    "FULL NAME_DataCard PRMp1_1": {},
    "galleryLTM": {},
    "galleryLTM_1": {},
    "galleryLTM_2": {},
    "galleryOT": {},
    "galleryPRMp1st_1": {},
    "galleryPRMp2nd_1": {},
    "galleryTemplate2": {},
    "galleryTemplate2_1": {},
    "galleryTemplate2_2": {},
    "galleryTemplate2_3": {},
    "galleryTemplate2_4": {},
    "galleryTemplate2_5": {},
    "galleryTemplate3": {},
    "galleryTemplate3_1": {},
    "galleryTemplate6": {},
    "galOCEP": {},
    "grpLTSearchMultipleLOB": {},
    "grpLTSearchMultipleOmnia": {},
    "grpNewOCForm": {},
    "grpOCECountry": {},
    "grpOCEPBillability": {},
    "grpOCEPBusUnit": {},
    "grpOCEPButtons": {},
    "grpOCEPCampaign": {},
    "grpOCEPClient": {},
    "grpOCEPEmpId": {},
    "grpOCEPEmpStatus": {},
    "grpOCEPFName": {},
    "grpOCEPHireDate": {},
    "grpOCEPLName": {},
    "grpOCEPLOB": {},
    "grpOCEPMName": {},
    "grpOCEPPosition": {},
    "grpOCEPRole": {},
    "grpOCEPSite": {},
    "grpOCEPStatus": {},
    "grpOCEPSubLOB": {},
    "grpOCEPSubUnit": {},
    "grpOCEPSupervisor": {},
    "grpOCFPButtons": {},
    "grpOCSPActions": {},
    "grpOCSPButtons": {},
    "grpOTLOB": {},
    "grpOTOmnia": {},
    "grpPRSearchMultipleLOB_1": {},
    "grpPRSearchMultipleOmnia_1": {},
    "HIRE DATE_Column1_1": {},
    "HIRE DATE_DataCardOCFP": {},
    "HomePage": {},
    "Host": {},
    "INTERNAL EMAIL": {},
    "INTERNSHIP_DataCard": {},
    "INTERNSHIP_DataCard_2": {},
    "INTERNSHIP_LTMDataCard": {},
    "Label1": {},
    "Label10": {},
    "Label11": {},
    "Label12": {},
    "Label13": {},
    "Label14": {},
    "Label15": {},
    "Label16": {},
    "Label17": {},
    "Label18": {},
    "Label19": {},
    "Label2": {},
    "Label20": {},
    "Label21": {},
    "Label22": {},
    "Label23": {},
    "Label24": {},
    "Label25": {},
    "Label26": {},
    "Label27": {},
    "Label28": {},
    "Label29": {},
    "Label3": {},
    "Label30": {},
    "Label31": {},
    "Label32": {},
    "Label33": {},
    "Label34": {},
    "Label35": {},
    "Label36": {},
    "Label37": {},
    "Label38": {},
    "Label39": {},
    "Label4": {},
    "Label40": {},
    "Label41": {},
    "Label5": {},
    "Label5_1": {},
    "Label5_10": {},
    "Label5_11": {},
    "Label5_12": {},
    "Label5_13": {},
    "Label5_14": {},
    "Label5_15": {},
    "Label5_16": {},
    "Label5_17": {},
    "Label5_18": {},
    "Label5_2": {},
    "Label5_3": {},
    "Label5_4": {},
    "Label5_5": {},
    "Label5_6": {},
    "Label5_7": {},
    "Label5_8": {},
    "Label5_9": {},
    "Label6": {},
    "Label7": {},
    "Label8": {},
    "Label9": {},
    "LAST NAME_Column1_1": {},
    "LAST NAME_DataCardOCFP": {},
    "lastDate_card": {},
    "lastDate_card_1": {},
    "lastDate_input": {},
    "lastDate_input_1": {},
    "lastDate_label": {},
    "lastDate_label_1": {},
    "Lateral Transfer Form_1": {},
    "Lateral Transfer Form_2": {},
    "Lateral Transfer Form_3": {},
    "Lateral Transfer Form_4": {},
    "Lateral Transfer Form_5": {},
    "Lateral Transfer Form_6": {},
    "LateralTransfer_FirstPage": {},
    "LateralTransfer_SecondPage": {},
    "LineOfBusiness_Label_1": {},
    "lname_card": {},
    "lname_card_1": {},
    "lname_label": {},
    "lname_label_1": {},
    "lname_value": {},
    "lname_value_1": {},
    "lob_card": {},
    "lob_card_1": {},
    "LOB_Column1_1": {},
    "LOB_DataCard1": {},
    "LOB_DataCard2": {},
    "LOB_DataCard3": {},
    "LOB_DataCard4": {},
    "LOB_DataCard7": {},
    "LOB_DataCardOCFP": {},
    "lob_input": {},
    "lob_label": {},
    "lob_Label": {},
    "lob_label_1": {},
    "LOB_OTDataCard1": {},
    "lob_value": {},
    "lob_value_1": {},
    "MIDDLE NAME_Column1_1": {},
    "MIDDLE NAME_DataCardOCFP": {},
    "MultipleTerminationForm_Label": {},
    "MultipleTerminationForm_Label_1": {},
    "NESTING START DATE_DataCard1": {},
    "NESTING START DATE_DataCard3": {},
    "NextArrow2": {},
    "NextArrow2_1": {},
    "NextArrow2_1_Verify_1": {},
    "NextArrow3": {},
    "NextArrow3_1": {},
    "NextArrow4": {},
    "NextArrow4_2": {},
    "NextArrow4_2_Verify_1": {},
    "oc1": {},
    "oc2": {},
    "oc3": {},
    "omnia_input": {},
    "OmniaCreation_EditPage": {},
    "OmniaCreation_FirstPage": {},
    "OmniaCreation_SecondPage": {},
    "omniaID": {},
    "omniaID_1": {},
    "OT1": {},
    "OT2": {},
    "OT3": {},
    "OT4": {},
    "OT5": {},
    "OT6": {},
    "Others_FirstPage": {},
    "Others_SecondPage": {},
    "position_card": {},
    "position_card_1": {},
    "POSITION_Column1_1": {},
    "POSITION_DataCard PRMp1_1": {},
    "POSITION_DataCardOCFP": {},
    "position_label": {},
    "position_label_1": {},
    "POSITION_LTMDataCard": {},
    "POSITION_LTMDataCard2": {},
    "POSITION_OTDataCard": {},
    "POSITION_OTDataCard1": {},
    "POSITION_PRMDataCard2_2": {},
    "position_value": {},
    "position_value_1": {},
    "proceed_btn": {},
    "proceed_btn_1": {},
    "PRODUCTION DATE_DataCard1": {},
    "PRODUCTION DATE_DataCard3": {},
    "Promotion Form p2_1": {},
    "Promotion Form_1": {},
    "Promotion_FirstPage": {},
    "Promotion_SecondPage": {},
    "rdLTMInternship": {},
    "rdPRInternship": {},
    "Rectangle1": {},
    "Rectangle2": {},
    "REGULARIZATION DATE_Column1": {},
    "Reminder": {},
    "Remove Button Container": {},
    "Remove_Button": {},
    "REMOVE_BUTTON": {},
    "ROLE_Column1_1": {},
    "ROLE_DataCardOCFP": {},
    "Roster Update Selection": {},
    "Save Button Container": {},
    "Save_Button": {},
    "SCHEDULE_OTDataCard": {},
    "SCHEDULE_OTDataCard1": {},
    "Separator2": {},
    "Separator2_1": {},
    "Separator2_1_Verify_1": {},
    "Separator3": {},
    "Separator3_1": {},
    "Separator4": {},
    "Separator4_2": {},
    "Separator4_2_Verify_1": {},
    "SITE DataCard PRMp1_1": {},
    "SITE_Column1_1": {},
    "SITE_LTMDataCard": {},
    "SITE_LTMDataCard2": {},
    "SITE_OTDataCard": {},
    "SITE_OTDataCard1": {},
    "SITE_PRMDataCard_4": {},
    "START DATE_OTDataCard": {},
    "START DATE_OTDataCard1": {},
    "STATUS_Column1": {},
    "STATUS_DataCardOCFP": {},
    "STATUS_OTDataCard": {},
    "STATUS_OTDataCard1": {},
    "SUB UNIT_Column1_1": {},
    "SUB-LOB_Column1_1": {},
    "SUB-LOB_DataCardOCFP": {},
    "SUB-UNIT_DataCard PRMp1_1": {},
    "SUB-UNIT_DataCardOCFP": {},
    "SUB-UNIT_LTMDataCard": {},
    "SUB-UNIT_LTMDataCard2": {},
    "SUB-UNIT_OTDataCard": {},
    "SUB-UNIT_OTDataCard1": {},
    "SUB-UNIT_PRMDataCard2_2": {},
    "SUPERVISOR_Column1_1": {},
    "SUPERVISOR_DataCard PRMp1_1": {},
    "SUPERVISOR_LT": {},
    "SUPERVISOR_LTMDataCard": {},
    "SUPERVISOR_OTDataCard": {},
    "SUPERVISOR_OTDataCard1": {},
    "tblOCSP": {},
    "TEAM_DataCardOCFP": {},
    "TEAM_PRMDataCard2_2": {},
    "Termination Status Verify": {},
    "Termination_FirstPage": {},
    "Termination_VerificationPage": {},
    "terminationStatus_card": {},
    "terminationStatus_card_1": {},
    "terminationStatus_cb": {},
    "terminationStatus_label": {},
    "terminationStatus_label_1": {},
    "terminationType_card": {},
    "terminationType_card_1": {},
    "terminationType_cb": {},
    "terminationType_label": {},
    "terminationType_label_1": {},
    "Time_Zone": {},
    "TIME_ZONE": {},
    "trainer1": {},
    "Trainer1": {},
    "TRAINER1": {},
    "trainer2": {},
    "Trainer2": {},
    "TRAINER2": {},
    "trainer3": {},
    "Trainer3": {},
    "TRAINER3": {},
    "txtLTMultipleBillability2": {},
    "txtLTMultipleBusUnit2": {},
    "txtLTMultipleEmpId": {},
    "txtLTMultipleEmpId2": {},
    "txtLTMultipleName": {},
    "txtLTMultipleName_1": {},
    "txtLTMultipleName_2": {},
    "txtLTMultipleName_3": {},
    "txtLTMultipleOmnia": {},
    "txtLTMultipleOmnia_1": {},
    "txtLTMultipleOmnia_2": {},
    "txtLTMultiplePosition2": {},
    "txtLTMultipleSite": {},
    "txtLTMultipleSite2": {},
    "txtLTMultipleSubUnit2": {},
    "txtLTMutipleClient2": {},
    "txtLTSearchMultipleLOB": {},
    "txtLTSearchMultipleOmnia": {},
    "txtOCEPEmpId": {},
    "txtOCEPFName": {},
    "txtOCEPLName": {},
    "txtOCEPMName": {},
    "txtOCFPEmpId": {},
    "txtOCFPFName": {},
    "txtOCFPLName": {},
    "txtOCFPMName": {},
    "txtOCInternalEmail": {},
    "txtOTBillability1": {},
    "txtOTBusUnit1": {},
    "txtOTClient1": {},
    "txtOTEmpId": {},
    "txtOTEmpId1": {},
    "txtOTEndDate1": {},
    "txtOTLOB": {},
    "txtOTLOB1": {},
    "txtOTMName": {},
    "txtOTMOmnia": {},
    "txtOTNesting1": {},
    "txtOTOmnia": {},
    "txtOTPosition1": {},
    "txtOTProduction1": {},
    "txtOTSchedule": {},
    "txtOTSchedule1": {},
    "txtOTSite": {},
    "txtOTSite1": {},
    "txtOTStartdate1": {},
    "txtOTStatus1": {},
    "txtOTSubUnit1": {},
    "txtOTSupervisor1": {},
    "txtPREDp1_1": {},
    "txtPREDp2_1": {},
    "txtPRMultipleBILLpm2_1": {},
    "txtPRMultipleBUpm2_1": {},
    "txtPRMultipleCLpm2_1": {},
    "txtPRMultipleEmpName_1": {},
    "txtPRMultipleEmpNamepm2_1": {},
    "txtPRMultipleIdpm1_1": {},
    "txtPRMultipleNamepm1_1": {},
    "txtPRMultipleOmniapm1_1": {},
    "txtPRMultipleOmniapm2_1": {},
    "txtPRMultiplePOSpm2_1": {},
    "txtPRMultipleSite_1": {},
    "txtPRMultipleSitepm2_1": {},
    "txtPRMultipleSUpm2_1": {},
    "txtPRMultipleSUPpm2_1": {},
    "txtPRSearchMultipleLOB_1": {},
    "txtPRSearchMultipleOmnia_1": {},
    "txtPRSEp1_1": {},
    "txtPRUEp2_1": {}
  },
  "PCFDynamicSchemaForIRRetrievalEntry": {},
  "PCFTemplateEntry": {},
  "PublishOrderIndices": {
    "address_card": 568,
    "address_card_1": 619,
    "address_input": 570,
    "address_input_1": 621,
    "address_label": 569,
    "address_label_1": 620,
    "App": 0,
    "BILLABILITY_Column1_1": 95,
    "BILLABILITY_DataCard PRMp1_1": 464,
    "BILLABILITY_DataCardOCFP": 57,
    "BILLABILITY_LTMDataCard": 210,
    "BILLABILITY_LTMDataCard2": 250,
    "BILLABILITY_OTDataCard": 318,
    "BILLABILITY_OTDataCard1": 392,
    "BILLABILITY_PRMDataCard2_2": 510,
    "btnFirstPageNext": 6,
    "btnLTMultipleBack": 220,
    "btnLTMultipleBack_1": 267,
    "btnLTMultipleBack_2": 421,
    "btnLTMultipleBack_3": 576,
    "btnLTMultipleBack_4": 627,
    "btnLTMultipleReview": 221,
    "btnLTMultipleReview_1": 268,
    "btnLTMultipleReview_2": 422,
    "btnLTRemove": 260,
    "btnLTRemove_1": 626,
    "btnOCEPBack": 168,
    "btnOCEPUpdate": 169,
    "btnOCFPBack": 76,
    "btnOCFPReview": 78,
    "btnOCFPSave": 75,
    "btnOCSPBack": 104,
    "btnOCSPEdit": 80,
    "btnOCSPRemove": 82,
    "btnOCSPSubmit": 106,
    "btnOTBack": 347,
    "btnOTRemove": 420,
    "btnOTReview": 348,
    "btnOTSave": 346,
    "btnPRMultipleBackp1_1": 474,
    "btnPRMultipleBackp2_1": 521,
    "btnPRMultipleReviewp1_1": 475,
    "btnPRMultipleSubmitp2_1": 522,
    "btnPRRemovep2_3": 520,
    "BUSINESS UNIT_Column1_1": 89,
    "BUSINESS UNIT_DataCard PRMp1_1": 446,
    "BUSINESS UNIT_DataCardOCFP": 29,
    "BUSINESS UNIT_LTMDataCard": 192,
    "BUSINESS UNIT_LTMDataCard2": 232,
    "BUSINESS UNIT_OTDataCard": 288,
    "BUSINESS UNIT_OTDataCard1": 362,
    "BUSINESS UNIT_PRMDataCard_4": 492,
    "Button1": 74,
    "Button2": 575,
    "Button3": 219,
    "Button4": 473,
    "campaign_card": 553,
    "campaign_card_1": 604,
    "CAMPAIGN_Column1_1": 93,
    "campaign_label": 554,
    "campaign_label_1": 605,
    "campaign_value": 555,
    "campaign_value_1": 606,
    "cbLTMultipleBillability": 211,
    "cbLTMultipleBusUnit": 193,
    "cbLTMultipleClient": 205,
    "cbLTMultipleLOB": 208,
    "cbLTMultiplePosition": 199,
    "cbLTMultipleSubUnit": 196,
    "cbLTMultipleSupervisor": 214,
    "cbLTSearchMultipleLOB": 173,
    "cbLTSearchMultipleOmnia": 175,
    "cbOCEPBillability": 167,
    "cbOCEPBusUnit": 134,
    "cbOCEPCampaign": 144,
    "cbOCEPClient": 135,
    "cbOCEPCountry": 145,
    "cbOCEPEmpStatus": 166,
    "cbOCEPLOB": 152,
    "cbOCEPPosition": 151,
    "cbOCEPRole": 160,
    "cbOCEPSite": 153,
    "cbOCEPStatus": 161,
    "cbOCEPSubLOB": 159,
    "cbOCEPSubUnit": 143,
    "cbOCEPSupervisor": 136,
    "cbOCFPBillability": 59,
    "cbOCFPBusUnit": 31,
    "cbOCFPClient": 47,
    "cbOCFPCountry": 66,
    "cbOCFPDivision": 50,
    "cbOCFPEmpStatus": 43,
    "cbOCFPLOB": 53,
    "cbOCFPPosition": 37,
    "cbOCFPRole": 72,
    "cbOCFPSite": 69,
    "cbOCFPStatus": 40,
    "cbOCFPSubLOB": 56,
    "cbOCFPSubUnit": 34,
    "cbOCFPSupervisor": 63,
    "cbOTBillability": 319,
    "cbOTBusUnit": 289,
    "cbOTClient": 307,
    "cbOTLOB": 313,
    "cbOTOmnia": 274,
    "cbOTPosition": 301,
    "cbOTSearchLOB": 273,
    "cbOTStatus": 298,
    "cbOTSubUnit": 295,
    "cbOTSupervisor": 328,
    "cbPRMultipleBillability_1": 465,
    "cbPRMultipleBusUnit_1": 447,
    "cbPRMultipleClient_1": 459,
    "cbPRMultipleLOB_2": 462,
    "cbPRMultiplePosition_1": 453,
    "cbPRMultipleSubUnit_1": 450,
    "cbPRMultipleSupervisor_1": 468,
    "cbPRSearchMultipleLOB": 427,
    "cbPRSearchMultipleOmnia": 428,
    "class_name": 335,
    "Class_Name": 407,
    "CLASS_NAME": 334,
    "ClassName": 333,
    "CLIENT_Column1_1": 92,
    "CLIENT_DataCard PRMp1_1": 458,
    "CLIENT_DataCardOCFP": 45,
    "CLIENT_LTMDataCard": 204,
    "CLIENT_LTMDataCard2": 244,
    "CLIENT_OTDataCard": 306,
    "CLIENT_OTDataCard1": 380,
    "CLIENT_PRMDataCard2_2": 504,
    "comment_card": 571,
    "comment_card_1": 622,
    "comment_input": 573,
    "comment_input_1": 624,
    "comment_label": 572,
    "comment_label_1": 623,
    "COUNTRY_Column1_1": 96,
    "COUNTRY_DataCardOCFP": 64,
    "DataCard1": 259,
    "DataCard12": 41,
    "DataCard6": 516,
    "DataCard7": 241,
    "DataCard8": 48,
    "DataCard9": 67,
    "DataCardKey1": 228,
    "DataCardKey1_1": 360,
    "DataCardKey10": 20,
    "DataCardKey11": 23,
    "DataCardKey13": 317,
    "DataCardKey14": 323,
    "DataCardKey15_1": 33,
    "DataCardKey16_1": 36,
    "DataCardKey18": 390,
    "DataCardKey19": 396,
    "DataCardKey2": 209,
    "DataCardKey24": 187,
    "DataCardKey24_1": 286,
    "DataCardKey27": 372,
    "DataCardKey28": 378,
    "DataCardKey29": 384,
    "DataCardKey3": 463,
    "DataCardKey33": 46,
    "DataCardKey35": 55,
    "DataCardKey36": 236,
    "DataCardKey36_1": 369,
    "DataCardKey37": 194,
    "DataCardKey37_1": 233,
    "DataCardKey37_2": 290,
    "DataCardKey37_3": 363,
    "DataCardKey38": 197,
    "DataCardKey38_1": 296,
    "DataCardKey39": 206,
    "DataCardKey39_1": 308,
    "DataCardKey4": 248,
    "DataCardKey40": 212,
    "DataCardKey40_1": 320,
    "DataCardKey41": 200,
    "DataCardKey41_1": 302,
    "DataCardKey42": 215,
    "DataCardKey42_1": 329,
    "DataCardKey43_1": 326,
    "DataCardKey44": 239,
    "DataCardKey44_1": 375,
    "DataCardKey45": 245,
    "DataCardKey45_1": 381,
    "DataCardKey46": 52,
    "DataCardKey47": 190,
    "DataCardKey47_1": 230,
    "DataCardKey47_2": 292,
    "DataCardKey47_3": 366,
    "DataCardKey48": 58,
    "DataCardKey49": 62,
    "DataCardKey5": 314,
    "DataCardKey50": 251,
    "DataCardKey50_1": 393,
    "DataCardKey51_1": 399,
    "DataCardKey52_1": 402,
    "DataCardKey53": 65,
    "DataCardKey55": 71,
    "DataCardKey56": 11,
    "DataCardKey6": 14,
    "DataCardKey7": 387,
    "DataCardKey8": 508,
    "DataCardKey9": 17,
    "DataCardKeyBILLpm1_1": 466,
    "DataCardKeyBILLPRpm2_1": 512,
    "DataCardKeyBUpm1_1": 448,
    "DataCardKeyBUPRpm2_1": 493,
    "DataCardKeyCLpm1_1": 460,
    "DataCardKeyCLPRpm2_1": 505,
    "DataCardKeyENpm1_1": 441,
    "DataCardKeyENPRpm2_1": 487,
    "DataCardKeyPOSpm1_1": 454,
    "DataCardKeyPOSPRpm2_1": 500,
    "DataCardKeySITEpm1_1": 444,
    "DataCardKeySITEPRpm2_1": 490,
    "DataCardKeySUpm1_1": 451,
    "DataCardKeySUPpm1_1": 469,
    "DataCardKeySUPPRpm2_1": 514,
    "DataCardKeySUPRpm2_1": 497,
    "DataCardValue2": 249,
    "DataCardValue4": 509,
    "dateEnd": 310,
    "dateNesting": 316,
    "dateOCEPHireDate": 165,
    "dateOCFPHireDate": 24,
    "dateProduction": 322,
    "dateStart": 304,
    "dpLTEffectivityDate": 217,
    "dpPREffectivityDate": 471,
    "drpOTtimezone": 331,
    "drpRosterSelection": 5,
    "EFFECTIVITY_DATE": 470,
    "EFFECTIVITY_DATE_LT": 216,
    "effectivityDate_card": 562,
    "effectivityDate_card_1": 613,
    "effectivityDate_input": 564,
    "effectivityDate_input_1": 615,
    "effectivityDate_label": 563,
    "effectivityDate_label_1": 614,
    "EFFECTIVITYDATE_LT": 256,
    "email_card": 550,
    "email_card_1": 601,
    "email_label": 551,
    "email_label_1": 603,
    "email_value": 552,
    "email_value_1": 602,
    "EMPLOYEE ID_Column1_1": 84,
    "EMPLOYEE ID_DataCard1": 226,
    "EMPLOYEE ID_DataCardOCFP": 10,
    "EMPLOYEE ID_LTMDataCard": 186,
    "EMPLOYEE ID_OTDataCard": 285,
    "EMPLOYEE ID_OTDataCard1": 359,
    "EMPLOYEE NAME_PRMDataCard_3": 486,
    "EmployeeGallery": 530,
    "EmployeeGallery_1": 581,
    "employeeID": 535,
    "employeeID_1": 586,
    "EmployeeInfo_form": 537,
    "EmployeeInfo_form_1": 588,
    "employeeInfo_label": 529,
    "employeeInfo_label_1": 580,
    "employeeList_label": 528,
    "employeeList_label_1": 579,
    "employeeName": 532,
    "employeeName_1": 583,
    "EMPLOYMENT STATUS_Column1": 100,
    "END DATE_OTDataCard": 309,
    "END DATE_OTDataCard1": 383,
    "FIRST NAME_Column1_1": 85,
    "FIRST NAME_DataCardOCFP": 13,
    "fname_card": 538,
    "fname_card_1": 589,
    "fname_label": 539,
    "fname_label_1": 590,
    "fname_value": 540,
    "fname_value_1": 591,
    "formLTM": 185,
    "formLTM2": 225,
    "formOCFirstPage1": 9,
    "formOCFirstPage2": 28,
    "formOCFirstPage3": 44,
    "formOCFirstPage4": 60,
    "formOT": 284,
    "formOT1": 358,
    "formPREDsp2": 439,
    "formPREDsp2_1": 485,
    "FULL NAME_DataCard PRMp1_1": 440,
    "galleryLTM": 179,
    "galleryLTM_1": 261,
    "galleryLTM_2": 352,
    "galleryOT": 278,
    "galleryPRMp1st_1": 432,
    "galleryPRMp2nd_1": 479,
    "galleryTemplate2": 180,
    "galleryTemplate2_1": 262,
    "galleryTemplate2_2": 279,
    "galleryTemplate2_3": 353,
    "galleryTemplate2_4": 433,
    "galleryTemplate2_5": 480,
    "galleryTemplate3": 531,
    "galleryTemplate3_1": 582,
    "galleryTemplate6": 111,
    "galOCEP": 109,
    "grpLTSearchMultipleLOB": 172,
    "grpLTSearchMultipleOmnia": 174,
    "grpNewOCForm": 73,
    "grpOCECountry": 117,
    "grpOCEPBillability": 110,
    "grpOCEPBusUnit": 129,
    "grpOCEPButtons": 107,
    "grpOCEPCampaign": 121,
    "grpOCEPClient": 120,
    "grpOCEPEmpId": 137,
    "grpOCEPEmpStatus": 132,
    "grpOCEPFName": 124,
    "grpOCEPHireDate": 127,
    "grpOCEPLName": 126,
    "grpOCEPLOB": 122,
    "grpOCEPMName": 125,
    "grpOCEPPosition": 131,
    "grpOCEPRole": 119,
    "grpOCEPSite": 118,
    "grpOCEPStatus": 128,
    "grpOCEPSubLOB": 123,
    "grpOCEPSubUnit": 130,
    "grpOCEPSupervisor": 116,
    "grpOCFPButtons": 77,
    "grpOCSPActions": 81,
    "grpOCSPButtons": 105,
    "grpOTLOB": 270,
    "grpOTOmnia": 271,
    "grpPRSearchMultipleLOB_1": 423,
    "grpPRSearchMultipleOmnia_1": 424,
    "HIRE DATE_Column1_1": 88,
    "HIRE DATE_DataCardOCFP": 22,
    "HomePage": 2,
    "Host": 0,
    "INTERNAL EMAIL": 25,
    "INTERNSHIP_DataCard": 455,
    "INTERNSHIP_DataCard_2": 501,
    "INTERNSHIP_LTMDataCard": 201,
    "Label1": 609,
    "Label10": 344,
    "Label11": 503,
    "Label12": 502,
    "Label13": 202,
    "Label14": 408,
    "Label15": 243,
    "Label16": 242,
    "Label17": 411,
    "Label18": 332,
    "Label19": 2,
    "Label2": 299,
    "Label20": 405,
    "Label21": 406,
    "Label22": 49,
    "Label23": 4,
    "Label24": 68,
    "Label25": 30,
    "Label26": 414,
    "Label27": 39,
    "Label28": 417,
    "Label29": 42,
    "Label3": 305,
    "Label30": 412,
    "Label31": 418,
    "Label32": 409,
    "Label33": 415,
    "Label34": 257,
    "Label35": 258,
    "Label36": 254,
    "Label37": 26,
    "Label38": 255,
    "Label39": 472,
    "Label4": 311,
    "Label40": 517,
    "Label41": 518,
    "Label5": 112,
    "Label5_1": 138,
    "Label5_10": 114,
    "Label5_11": 140,
    "Label5_12": 148,
    "Label5_13": 155,
    "Label5_14": 115,
    "Label5_15": 141,
    "Label5_16": 149,
    "Label5_17": 156,
    "Label5_18": 164,
    "Label5_2": 146,
    "Label5_3": 154,
    "Label5_4": 162,
    "Label5_5": 113,
    "Label5_6": 139,
    "Label5_7": 147,
    "Label5_8": 163,
    "Label5_9": 157,
    "Label6": 218,
    "Label7": 456,
    "Label8": 337,
    "Label9": 341,
    "LAST NAME_Column1_1": 87,
    "LAST NAME_DataCardOCFP": 19,
    "lastDate_card": 565,
    "lastDate_card_1": 616,
    "lastDate_input": 567,
    "lastDate_input_1": 618,
    "lastDate_label": 566,
    "lastDate_label_1": 617,
    "Lateral Transfer Form_1": 170,
    "Lateral Transfer Form_2": 177,
    "Lateral Transfer Form_3": 178,
    "Lateral Transfer Form_4": 222,
    "Lateral Transfer Form_5": 223,
    "Lateral Transfer Form_6": 224,
    "LateralTransfer_FirstPage": 0,
    "LateralTransfer_SecondPage": 0,
    "LineOfBusiness_Label_1": 526,
    "lname_card": 541,
    "lname_card_1": 592,
    "lname_label": 542,
    "lname_label_1": 594,
    "lname_value": 543,
    "lname_value_1": 593,
    "lob_card": 547,
    "lob_card_1": 598,
    "LOB_Column1_1": 94,
    "LOB_DataCard1": 207,
    "LOB_DataCard2": 461,
    "LOB_DataCard3": 247,
    "LOB_DataCard4": 312,
    "LOB_DataCard7": 507,
    "LOB_DataCardOCFP": 51,
    "lob_input": 525,
    "lob_label": 548,
    "lob_Label": 524,
    "lob_label_1": 600,
    "LOB_OTDataCard1": 386,
    "lob_value": 549,
    "lob_value_1": 599,
    "MIDDLE NAME_Column1_1": 86,
    "MIDDLE NAME_DataCardOCFP": 16,
    "MultipleTerminationForm_Label": 523,
    "MultipleTerminationForm_Label_1": 578,
    "NESTING START DATE_DataCard1": 315,
    "NESTING START DATE_DataCard3": 389,
    "NextArrow2": 182,
    "NextArrow2_1": 281,
    "NextArrow2_1_Verify_1": 435,
    "NextArrow3": 264,
    "NextArrow3_1": 355,
    "NextArrow4": 533,
    "NextArrow4_2": 584,
    "NextArrow4_2_Verify_1": 482,
    "oc1": 7,
    "oc2": 79,
    "oc3": 108,
    "omnia_input": 527,
    "OmniaCreation_EditPage": 0,
    "OmniaCreation_FirstPage": 0,
    "OmniaCreation_SecondPage": 0,
    "omniaID": 534,
    "omniaID_1": 585,
    "OT1": 269,
    "OT2": 276,
    "OT3": 277,
    "OT4": 351,
    "OT5": 350,
    "OT6": 349,
    "Others_FirstPage": 0,
    "Others_SecondPage": 0,
    "position_card": 544,
    "position_card_1": 595,
    "POSITION_Column1_1": 91,
    "POSITION_DataCard PRMp1_1": 452,
    "POSITION_DataCardOCFP": 35,
    "position_label": 545,
    "position_label_1": 596,
    "POSITION_LTMDataCard": 198,
    "POSITION_LTMDataCard2": 238,
    "POSITION_OTDataCard": 300,
    "POSITION_OTDataCard1": 374,
    "POSITION_PRMDataCard2_2": 498,
    "position_value": 546,
    "position_value_1": 597,
    "proceed_btn": 577,
    "proceed_btn_1": 628,
    "PRODUCTION DATE_DataCard1": 321,
    "PRODUCTION DATE_DataCard3": 395,
    "Promotion Form p2_1": 476,
    "Promotion Form_1": 425,
    "Promotion_FirstPage": 314,
    "Promotion_SecondPage": 362,
    "rdLTMInternship": 203,
    "rdPRInternship": 457,
    "Rectangle1": 8,
    "Rectangle2": 0,
    "REGULARIZATION DATE_Column1": 98,
    "Reminder": 1,
    "Remove Button Container": 625,
    "Remove_Button": 519,
    "REMOVE_BUTTON": 419,
    "ROLE_Column1_1": 97,
    "ROLE_DataCardOCFP": 70,
    "Roster Update Selection": 3,
    "Save Button Container": 574,
    "Save_Button": 345,
    "SCHEDULE_OTDataCard": 324,
    "SCHEDULE_OTDataCard1": 398,
    "Separator2": 184,
    "Separator2_1": 283,
    "Separator2_1_Verify_1": 438,
    "Separator3": 266,
    "Separator3_1": 357,
    "Separator4": 536,
    "Separator4_2": 587,
    "Separator4_2_Verify_1": 484,
    "SITE DataCard PRMp1_1": 443,
    "SITE_Column1_1": 103,
    "SITE_LTMDataCard": 189,
    "SITE_LTMDataCard2": 229,
    "SITE_OTDataCard": 291,
    "SITE_OTDataCard1": 365,
    "SITE_PRMDataCard_4": 489,
    "START DATE_OTDataCard": 303,
    "START DATE_OTDataCard1": 377,
    "STATUS_Column1": 99,
    "STATUS_DataCardOCFP": 38,
    "STATUS_OTDataCard": 297,
    "STATUS_OTDataCard1": 371,
    "SUB UNIT_Column1_1": 90,
    "SUB-LOB_Column1_1": 101,
    "SUB-LOB_DataCardOCFP": 54,
    "SUB-UNIT_DataCard PRMp1_1": 449,
    "SUB-UNIT_DataCardOCFP": 32,
    "SUB-UNIT_LTMDataCard": 195,
    "SUB-UNIT_LTMDataCard2": 235,
    "SUB-UNIT_OTDataCard": 294,
    "SUB-UNIT_OTDataCard1": 368,
    "SUB-UNIT_PRMDataCard2_2": 495,
    "SUPERVISOR_Column1_1": 102,
    "SUPERVISOR_DataCard PRMp1_1": 467,
    "SUPERVISOR_LT": 253,
    "SUPERVISOR_LTMDataCard": 213,
    "SUPERVISOR_OTDataCard": 327,
    "SUPERVISOR_OTDataCard1": 401,
    "tblOCSP": 83,
    "TEAM_DataCardOCFP": 61,
    "TEAM_PRMDataCard2_2": 513,
    "Termination Status Verify": 612,
    "Termination_FirstPage": 208,
    "Termination_VerificationPage": 264,
    "terminationStatus_card": 559,
    "terminationStatus_card_1": 610,
    "terminationStatus_cb": 561,
    "terminationStatus_label": 560,
    "terminationStatus_label_1": 611,
    "terminationType_card": 556,
    "terminationType_card_1": 607,
    "terminationType_cb": 558,
    "terminationType_label": 557,
    "terminationType_label_1": 608,
    "Time_Zone": 330,
    "TIME_ZONE": 404,
    "trainer1": 338,
    "Trainer1": 410,
    "TRAINER1": 336,
    "trainer2": 340,
    "Trainer2": 413,
    "TRAINER2": 339,
    "trainer3": 343,
    "Trainer3": 416,
    "TRAINER3": 342,
    "txtLTMultipleBillability2": 252,
    "txtLTMultipleBusUnit2": 234,
    "txtLTMultipleEmpId": 188,
    "txtLTMultipleEmpId2": 227,
    "txtLTMultipleName": 181,
    "txtLTMultipleName_1": 263,
    "txtLTMultipleName_2": 354,
    "txtLTMultipleName_3": 481,
    "txtLTMultipleOmnia": 183,
    "txtLTMultipleOmnia_1": 265,
    "txtLTMultipleOmnia_2": 356,
    "txtLTMultiplePosition2": 240,
    "txtLTMultipleSite": 191,
    "txtLTMultipleSite2": 231,
    "txtLTMultipleSubUnit2": 237,
    "txtLTMutipleClient2": 246,
    "txtLTSearchMultipleLOB": 171,
    "txtLTSearchMultipleOmnia": 176,
    "txtOCEPEmpId": 133,
    "txtOCEPFName": 142,
    "txtOCEPLName": 158,
    "txtOCEPMName": 150,
    "txtOCFPEmpId": 12,
    "txtOCFPFName": 15,
    "txtOCFPLName": 21,
    "txtOCFPMName": 18,
    "txtOCInternalEmail": 27,
    "txtOTBillability1": 394,
    "txtOTBusUnit1": 364,
    "txtOTClient1": 382,
    "txtOTEmpId": 287,
    "txtOTEmpId1": 361,
    "txtOTEndDate1": 385,
    "txtOTLOB": 272,
    "txtOTLOB1": 388,
    "txtOTMName": 280,
    "txtOTMOmnia": 282,
    "txtOTNesting1": 391,
    "txtOTOmnia": 275,
    "txtOTPosition1": 376,
    "txtOTProduction1": 397,
    "txtOTSchedule": 325,
    "txtOTSchedule1": 400,
    "txtOTSite": 293,
    "txtOTSite1": 367,
    "txtOTStartdate1": 379,
    "txtOTStatus1": 373,
    "txtOTSubUnit1": 370,
    "txtOTSupervisor1": 403,
    "txtPREDp1_1": 431,
    "txtPREDp2_1": 478,
    "txtPRMultipleBILLpm2_1": 511,
    "txtPRMultipleBUpm2_1": 494,
    "txtPRMultipleCLpm2_1": 506,
    "txtPRMultipleEmpName_1": 442,
    "txtPRMultipleEmpNamepm2_1": 488,
    "txtPRMultipleIdpm1_1": 436,
    "txtPRMultipleNamepm1_1": 434,
    "txtPRMultipleOmniapm1_1": 437,
    "txtPRMultipleOmniapm2_1": 483,
    "txtPRMultiplePOSpm2_1": 499,
    "txtPRMultipleSite_1": 445,
    "txtPRMultipleSitepm2_1": 491,
    "txtPRMultipleSUpm2_1": 496,
    "txtPRMultipleSUPpm2_1": 515,
    "txtPRSearchMultipleLOB_1": 426,
    "txtPRSearchMultipleOmnia_1": 429,
    "txtPRSEp1_1": 430,
    "txtPRUEp2_1": 477
  },
  "ResourcesJsonIndices": {
    "Image-homeScreen": 4,
    "Image-homeScreen2": 5,
    "Image-MicrosoftTeams-image": 2,
    "Image-MicrosoftTeams-image (2)": 1,
    "Image-SampleImage": 0,
    "Image-Untitled design 29": 3
  },
  "RuleScreenIdWithoutScreen": {},
  "TemplateVersions": {},
  "VolatileProperties": {
    "AnalysisLoadTime": 4.7245915,
    "ControlCount": {
      "button": 35,
      "combobox": 61,
      "dataTable": 1,
      "dataTableColumn": 20,
      "datepicker": 12,
      "dropdown": 4,
      "form": 12,
      "gallery": 9,
      "galleryTemplate": 9,
      "group": 31,
      "htmlViewer": 12,
      "icon": 8,
      "label": 253,
      "radio": 2,
      "rectangle": 15,
      "screen": 12,
      "text": 14,
      "typedDataCard": 133
    },
    "DeserializationLoadTime": 4.8212064
  },
  "WasLocalDatabaseReferencesEmpty": true
}